calcazhurb/__init__.py
calcazhurb/calculator.py
calcazhurb-0.0.6.dist-info/LICENSE
calcazhurb-0.0.6.dist-info/METADATA
calcazhurb-0.0.6.dist-info/WHEEL
calcazhurb-0.0.6.dist-info/top_level.txt
calcazhurb-0.0.6.dist-info/RECORD
