Metadata-Version: 2.1
Name: calcazhurb
Version: 0.0.6
Summary: A Calculator package
Author-email: Andrii Zhurba <andrijzurba79@gmail.com>
Project-URL: Homepage, https://github.com/TuringCollegeSubmissions/azhurb-DWWP.1.5
Classifier: Programming Language :: Python :: 3
Classifier: License :: OSI Approved :: MIT License
Classifier: Operating System :: OS Independent
Requires-Python: >=3.8
License-File: LICENSE
